benchmark_tests/__init__.py
benchmark_tests/benchmark.py
benchmark_tests/mongita/__init__.py
benchmark_tests/mongita/collection.py
benchmark_tests/mongita/command_cursor.py
benchmark_tests/mongita/common.py
benchmark_tests/mongita/cursor.py
benchmark_tests/mongita/database.py
benchmark_tests/mongita/errors.py
benchmark_tests/mongita/mongita_client.py
benchmark_tests/mongita/mongitasync.py
benchmark_tests/mongita/read_concern.py
benchmark_tests/mongita/results.py
benchmark_tests/mongita/write_concern.py
benchmark_tests/mongita/engines/__init__.py
benchmark_tests/mongita/engines/disk_engine.py
benchmark_tests/mongita/engines/engine_common.py
benchmark_tests/mongita/engines/lmdb_backend.py
benchmark_tests/mongita/engines/lmdb_engine.py
benchmark_tests/mongita/engines/memory_engine.py
mongita/__init__.py
mongita/collection.py
mongita/command_cursor.py
mongita/common.py
mongita/cursor.py
mongita/database.py
mongita/errors.py
mongita/mongita_client.py
mongita/mongitasync.py
mongita/read_concern.py
mongita/results.py
mongita/write_concern.py
mongita/engines/__init__.py
mongita/engines/disk_engine.py
mongita/engines/engine_common.py
mongita/engines/lmdb_backend.py
mongita/engines/lmdb_engine.py
mongita/engines/memory_engine.py
mongita_lmdb-1.2.0.data/scripts/mongitasync
mongita_lmdb-1.2.0.dist-info/licenses/LICENSE
mongita_lmdb-1.2.0.dist-info/METADATA
mongita_lmdb-1.2.0.dist-info/WHEEL
mongita_lmdb-1.2.0.dist-info/top_level.txt
mongita_lmdb-1.2.0.dist-info/RECORD
