Metadata-Version: 2.4
Name: mongita_lmdb
Version: 1.2.0
Summary: Mongita is a lightweight embedded document database that implements a commonly-used subset of the MongoDB/PyMongo interface.
Home-page: https://github.com/cnmoro/mongita-lmdb
Download-URL: https://github.com/cnmoro/mongita-lmdb/archive/mongita-1.2.0.tar.gz
Author: Scott Rogowski
Author-email: scottmrogowski@gmail.com
Classifier: Programming Language :: Python :: 3
Classifier: License :: OSI Approved :: BSD License
Classifier: Operating System :: OS Independent
Requires-Python: >=3.7
License-File: LICENSE
Requires-Dist: pymongo<5.0,>=3.0
Requires-Dist: sortedcontainers<3.0,>=2.3
Requires-Dist: lmdb
Dynamic: author
Dynamic: author-email
Dynamic: classifier
Dynamic: description
Dynamic: description-content-type
Dynamic: download-url
Dynamic: home-page
Dynamic: license-file
Dynamic: requires-dist
Dynamic: requires-python
Dynamic: summary
